baton/__init__.py
baton/admin.py
baton/ai.py
baton/apps.py
baton/config.py
baton/fields.py
baton/models.py
baton/tests.py
baton/urls.py
baton/views.py
baton/widgets.py
baton/autodiscover/__init__.py
baton/autodiscover/admin.py
baton/locale/it/LC_MESSAGES/django.mo
baton/locale/it/LC_MESSAGES/django.po
baton/migrations/0001_initial.py
baton/migrations/0002_alter_batontheme_options_alter_batontheme_active_and_more.py
baton/migrations/__init__.py
baton/static/admin/css/base.css
baton/static/admin/css/changelists.css
baton/static/admin/css/dark_mode.css
baton/static/admin/css/dashboard.css
baton/static/admin/css/forms.css
baton/static/admin/css/responsive.css
baton/static/baton/app/.babelrc
baton/static/baton/app/.eslintignore
baton/static/baton/app/.eslintrc
baton/static/baton/app/.prettierrc.json
baton/static/baton/app/.tern-project
baton/static/baton/app/.tool-versions
baton/static/baton/app/package-lock.json
baton/static/baton/app/package.json
baton/static/baton/app/postcss.config.js
baton/static/baton/app/stats.json
baton/static/baton/app/webpack.common.js
baton/static/baton/app/webpack.dev.js
baton/static/baton/app/webpack.prod.js
baton/static/baton/app/dist/1d5b13020cf1d7efde67.svg
baton/static/baton/app/dist/227c93190fe7f82de3f8.woff2
baton/static/baton/app/dist/3ac6859b28be946745f9.woff2
baton/static/baton/app/dist/41c0f706d8ce93933771.woff2
baton/static/baton/app/dist/450a5c898f0b184b968b.ttf
baton/static/baton/app/dist/48af7707fe9e6494d6a5.woff
baton/static/baton/app/dist/62397fb22f9cf321cfcd.svg
baton/static/baton/app/dist/77ecb942e56f9b036426.woff
baton/static/baton/app/dist/7fd18804f2abd547c565.svg
baton/static/baton/app/dist/820a83e6dbb5ee491646.svg
baton/static/baton/app/dist/b009a76ad6afe4ebd301.woff2
baton/static/baton/app/dist/b1a653db79258eeccc5d.ttf
baton/static/baton/app/dist/baton.min.js
baton/static/baton/app/dist/baton.min.js.LICENSE.txt
baton/static/baton/app/dist/c2f7ab22cb9cbd074c3a.woff
baton/static/baton/app/dist/c48fb6765a9fcb00b330.woff2
django_baton_alt_theme-4.2.0.1.dist-info/LICENSE
django_baton_alt_theme-4.2.0.1.dist-info/METADATA
django_baton_alt_theme-4.2.0.1.dist-info/WHEEL
django_baton_alt_theme-4.2.0.1.dist-info/top_level.txt
django_baton_alt_theme-4.2.0.1.dist-info/RECORD
