Metadata-Version: 2.1
Name: django-baton-alt-theme
Version: 4.2.0.1
Summary: A cool, modern and responsive django admin application with an alternate theme
Home-page: https://github.com/blackbox-innovation/django-baton
Author: Krystof Beuermann
Author-email: krystof@blackbox.ms
License: MIT License
Project-URL: Documentation, https://django-baton.readthedocs.io/en/latest/
Project-URL: Demo, https://django-baton.sqrt64.it/admin
Project-URL: Source, https://github.com/blackbox-innovation/django-baton
Project-URL: Tracker, https://github.com/blackbox-innovation/django-baton/issues
Classifier: Development Status :: 5 - Production/Stable
Classifier: Environment :: Web Environment
Classifier: Framework :: Django
Classifier: Intended Audience :: Developers
Classifier: Intended Audience :: System Administrators
Classifier: License :: OSI Approved :: MIT License
Classifier: Operating System :: OS Independent
Classifier: Programming Language :: Python
Classifier: Programming Language :: Python :: 3.5
Classifier: Programming Language :: Python :: 3.6
Classifier: Programming Language :: Python :: 3.7
Classifier: Programming Language :: Python :: 3.8
Classifier: Programming Language :: Python :: 3.9
Classifier: Programming Language :: Python :: 3.10
Classifier: Programming Language :: Python :: 3.11
Classifier: Programming Language :: Python :: 3.12
Classifier: Framework :: Django :: 2.1
Classifier: Framework :: Django :: 2.2
Classifier: Framework :: Django :: 3.0
Classifier: Framework :: Django :: 3.1
Classifier: Framework :: Django :: 4.0
Classifier: Framework :: Django :: 4.1
Classifier: Framework :: Django :: 4.2
Classifier: Framework :: Django :: 5.0
Classifier: Topic :: Software Development
Classifier: Topic :: Software Development :: User Interfaces
License-File: LICENSE
Requires-Dist: requests
